pytest_allure_spec_coverage/__init__.py
pytest_allure_spec_coverage/common.py
pytest_allure_spec_coverage/config_provider.py
pytest_allure_spec_coverage/hooks.py
pytest_allure_spec_coverage/matcher.py
pytest_allure_spec_coverage/plugin.py
pytest_allure_spec_coverage/xdist_shared.py
pytest_allure_spec_coverage/models/__init__.py
pytest_allure_spec_coverage/models/collector.py
pytest_allure_spec_coverage/models/scenario.py
pytest_allure_spec_coverage/spec_collectors/__init__.py
pytest_allure_spec_coverage/spec_collectors/sphinx.py
pytest_allure_spec_coverage-0.0.2.dist-info/LICENSE
pytest_allure_spec_coverage-0.0.2.dist-info/METADATA
pytest_allure_spec_coverage-0.0.2.dist-info/WHEEL
pytest_allure_spec_coverage-0.0.2.dist-info/entry_points.txt
pytest_allure_spec_coverage-0.0.2.dist-info/top_level.txt
pytest_allure_spec_coverage-0.0.2.dist-info/RECORD
