Metadata-Version: 2.1
Name: pytest-allure-spec-coverage
Version: 0.0.2
Summary: The pytest plugin aimed to display test coverage of the specs(requirements) in Allure
Home-page: UNKNOWN
Author: UNKNOWN
Author-email: UNKNOWN
License: UNKNOWN
Platform: UNKNOWN
Classifier: Framework :: Pytest
Requires-Dist: pytest
Requires-Dist: allure-pytest
Requires-Dist: toml
Requires-Dist: docutils
Requires-Dist: pluggy
